logging_splunk_hec/__init__.py
logging_splunk_hec-1.0.0.dist-info/METADATA
logging_splunk_hec-1.0.0.dist-info/WHEEL
logging_splunk_hec-1.0.0.dist-info/top_level.txt
logging_splunk_hec-1.0.0.dist-info/RECORD
