Metadata-Version: 2.1
Name: logging-splunk-hec
Version: 1.0.0
Summary: A Python logging handler to sends logs to Splunk using HTTP event collector (HEC)
Home-page: https://github.com/abhinav-chittora/logging_splunk_hec.git
Author: abhinav-chittora
Author-email: chittora.abhinav@googlemail.com
License: GNU GPL-3.0
Platform: UNKNOWN
Classifier: Development Status :: 5 - Production/Stable
Classifier: Intended Audience :: Developers
Classifier: License :: OSI Approved :: GNU General Public License v3 (GPLv3)
Classifier: Natural Language :: English
Classifier: Operating System :: POSIX :: Linux
Classifier: Operating System :: MacOS :: MacOS X
Classifier: Operating System :: Microsoft :: Windows
Classifier: Programming Language :: Python
Classifier: Programming Language :: Python :: 2.7
Classifier: Programming Language :: Python :: 3.4
Classifier: Programming Language :: Python :: 3.5
Classifier: Programming Language :: Python :: 3.6
Classifier: Programming Language :: Python :: 3.7
Classifier: Programming Language :: Python :: 3.8
Classifier: Topic :: System :: Logging
Requires-Dist: requests (<3.0.0,>=2.6.0)
Requires-Dist: requests
